_ikedarts.c
setup.py
ikedarts/__init__.py
ikedarts/ikedarts.py
ikedarts-c/ikedarts.cpp
ikedarts-c/ikedarts.h
ikedarts-c/ikedarts_main.cpp
ikedarts.egg-info/PKG-INFO
ikedarts.egg-info/SOURCES.txt
ikedarts.egg-info/dependency_links.txt
ikedarts.egg-info/entry_points.txt
ikedarts.egg-info/top_level.txt