Metadata-Version: 1.0
Name: ikedarts
Version: 0.1.2
Summary: Python interface to DARTS by Kudo Taku.
Home-page: https://github.com/tengu/ikedarts
Author: tengu
Author-email: karasuyamatengu@gmail.com
License: LGPL
Platform: UNKNOWN
